build/lib/build/lib/era5grib/__init__.py
build/lib/build/lib/era5grib/_version.py
build/lib/build/lib/era5grib/command_line.py
build/lib/build/lib/era5grib/config.py
build/lib/build/lib/era5grib/domain.py
build/lib/build/lib/era5grib/era5grib.py
build/lib/build/lib/era5grib/logging.py
build/lib/build/lib/era5grib/main.py
build/lib/build/lib/era5grib/parallel.py
build/lib/build/lib/era5grib/conftree/__init__.py
build/lib/build/lib/era5grib/data_handling/data_combine.py
build/lib/build/lib/era5grib/data_handling/data_read.py
build/lib/build/lib/era5grib/data_handling/era5field.py
build/lib/build/lib/era5grib/data_handling/grib_metadata.py
build/lib/build/lib/era5grib/data_handling/xarray_legacy_read.py
build/lib/build/lib/era5grib/output_drivers/grib.py
build/lib/build/lib/era5grib/output_drivers/netcdf.py
build/lib/era5grib/__init__.py
build/lib/era5grib/_version.py
build/lib/era5grib/command_line.py
build/lib/era5grib/config.py
build/lib/era5grib/domain.py
build/lib/era5grib/era5grib.py
build/lib/era5grib/logging.py
build/lib/era5grib/main.py
build/lib/era5grib/parallel.py
build/lib/era5grib/conftree/__init__.py
build/lib/era5grib/data_handling/data_combine.py
build/lib/era5grib/data_handling/data_read.py
build/lib/era5grib/data_handling/era5field.py
build/lib/era5grib/data_handling/grib_metadata.py
build/lib/era5grib/data_handling/xarray_legacy_read.py
build/lib/era5grib/output_drivers/grib.py
build/lib/era5grib/output_drivers/netcdf.py
era5grib/__init__.py
era5grib/_version.py
era5grib/command_line.py
era5grib/config.py
era5grib/domain.py
era5grib/era5grib.py
era5grib/logging.py
era5grib/main.py
era5grib/nci_regrid_weights.nc
era5grib/parallel.py
era5grib/config/defaults.yaml
era5grib/config/um_era5.yaml
era5grib/config/um_era5land.yaml
era5grib/config/wrf_era5.yaml
era5grib/config/wrf_era5land.yaml
era5grib/conftree/__init__.py
era5grib/data_handling/data_combine.py
era5grib/data_handling/data_read.py
era5grib/data_handling/era5field.py
era5grib-2.0.2.dist-info/LICENSE
era5grib-2.0.2.dist-info/METADATA
era5grib-2.0.2.dist-info/WHEEL
era5grib-2.0.2.dist-info/entry_points.txt
era5grib-2.0.2.dist-info/top_level.txt
era5grib-2.0.2.dist-info/RECORD
