Metadata-Version: 2.1
Name: era5grib
Version: 2.0.2
Summary: Convert ERA5 data on NCI to WRF/UM input formatted GRIB data
Author-email: Dale Roberts <dsroberts@unimelb.edu.au>, Scott Wales <scott.wales@bom.gov.au>
Requires-Python: >=3.9
License-File: LICENSE
Requires-Dist: xarray
Requires-Dist: pandas
Requires-Dist: intake
Requires-Dist: intake-esm
Requires-Dist: xesmf
Requires-Dist: numpy
Requires-Dist: mule
Requires-Dist: f90nml
Requires-Dist: cdo
Requires-Dist: distributed
